etsyapiv3sdk/__init__.py
etsyapiv3sdk/models/Listing.py
etsyapiv3sdk/models/ListingImage.py
etsyapiv3sdk/models/ListingProperty.py
etsyapiv3sdk/models/Price.py
etsyapiv3sdk/models/ProductionPartner.py
etsyapiv3sdk/models/Receipt.py
etsyapiv3sdk/models/Review.py
etsyapiv3sdk/models/Shipment.py
etsyapiv3sdk/models/ShippingProfile.py
etsyapiv3sdk/models/ShippingProfileDestination.py
etsyapiv3sdk/models/ShippingProfileUpgrade.py
etsyapiv3sdk/models/Shop.py
etsyapiv3sdk/models/Transaction.py
etsyapiv3sdk/models/Translation.py
etsyapiv3sdk/models/User.py
etsyapiv3sdk/models/Variation.py
etsyapiv3sdk/models/__init__.py
etsyapiv3sdk/resources/ListingResource.py
etsyapiv3sdk/resources/ReceiptResource.py
etsyapiv3sdk/resources/ReviewResource.py
etsyapiv3sdk/resources/ShopResource.py
etsyapiv3sdk/resources/TransactionResource.py
etsyapiv3sdk/resources/__init__.py
etsyapiv3sdk/utils/APIV3.py
etsyapiv3sdk/utils/RequestException.py
etsyapiv3sdk/utils/Response.py
etsyapiv3sdk/utils/__init__.py
etsy_apiv3_sdk-1.0.4.dist-info/METADATA
etsy_apiv3_sdk-1.0.4.dist-info/WHEEL
etsy_apiv3_sdk-1.0.4.dist-info/top_level.txt
etsy_apiv3_sdk-1.0.4.dist-info/RECORD
