Metadata-Version: 2.1
Name: etsy-apiv3-sdk
Version: 1.0.4
Summary: Etsy APIV3 SDK
Author: Esat Yılmaz
Author-email: esatyilmaz3500@gmail.com
Classifier: Programming Language :: Python :: 3.9
Classifier: License :: OSI Approved :: MIT License
Classifier: Operating System :: OS Independent
Requires-Python: >=3.5.5
Requires-Dist: pydantic
Requires-Dist: requests
Requires-Dist: requests-oauthlib
